partial_dependence.py
partial_dependence-0.0.5.dist-info/DESCRIPTION.rst
partial_dependence-0.0.5.dist-info/METADATA
partial_dependence-0.0.5.dist-info/RECORD
partial_dependence-0.0.5.dist-info/WHEEL
partial_dependence-0.0.5.dist-info/metadata.json
partial_dependence-0.0.5.dist-info/top_level.txt
