Metadata-Version: 2.0
Name: partial-dependence
Version: 0.0.5
Summary: PartialDependence is a library for visualizing input-output relationships of machine learning models.
Home-page: https://github.com/nyuvis/partial_dependence
Author: Paolo Tamagnini, Josua Krause, Enrico Bertini
Author-email: paolotamag@gmail.com,josua.krause@nyu.edu,enrico.bertini@nyu.edu
License: MIT
